rich_simple_term_menu/__init__.py
rich_simple_term_menu/simple_term_menu.py
rich_simple_term_menu-0.1.0.dist-info/LICENSE
rich_simple_term_menu-0.1.0.dist-info/METADATA
rich_simple_term_menu-0.1.0.dist-info/WHEEL
rich_simple_term_menu-0.1.0.dist-info/RECORD
