Metadata-Version: 2.1
Name: rich-simple-term-menu
Version: 0.1.0
Summary: Simple Term Menu with support for another print
Author: Dimitri Wyzlic
Author-email: dimitriwyzlic@gmail.com
Requires-Python: >=3.7.0,<4.0.0
Classifier: Programming Language :: Python :: 3
Classifier: Programming Language :: Python :: 3.7
Classifier: Programming Language :: Python :: 3.8
Classifier: Programming Language :: Python :: 3.9
Classifier: Programming Language :: Python :: 3.10
Classifier: Programming Language :: Python :: 3.11
